{
  "player1": {
    "imageUrl": "https://vignette.wikia.nocookie.net/finalfantasy/images/e/e7/FFX_Artwork_Tidus.png/revision/latest?cb=20180309234959",
    "title": "Tidus",
    "description": "Star player for the Besaid Aurochs, formerly of the Zanarkand Abes.",
    "uid": "OWWIypVjSEVEH4oYbm4lPSSvxXC3",
    "teamId": "team1"
  },
  "player2": {
    "imageUrl": "https://vignette.wikia.nocookie.net/finalfantasy/images/a/ad/FFX_Wakka_Art.png/revision/latest?cb=20140809030123",
    "title": "Wakka",
    "description": "Team captain and Right Forward of the Besaid Aurochs",
    "uid": "OWWIypVjSEVEH4oYbm4lPSSvxXC3",
    "teamId": "team1"
  },
  "player3": {
    "imageUrl": "https://vignette.wikia.nocookie.net/finalfantasy/images/e/e4/Datto.jpg/revision/latest?cb=20111203055223",
    "title": "Datto",
    "description": "Left Foward for the Besaid Aurochs",
    "uid": "OWWIypVjSEVEH4oYbm4lPSSvxXC3",
    "teamId": "team1"
  },
  "player4": {
    "imageUrl": "https://vignette.wikia.nocookie.net/finalfantasy/images/c/c8/Letty.jpg/revision/latest?cb=20110519043057",
    "title": "Letty",
    "description": "Midfielder for the Besaid Aurochs",
    "uid": "OWWIypVjSEVEH4oYbm4lPSSvxXC3",
    "teamId": "team1"
  },
  "player5": {
    "imageUrl": "https://vignette.wikia.nocookie.net/finalfantasy/images/e/ef/Jassu.jpg/revision/latest?cb=20110519041634",
    "title": "Jassu",
    "description": "Left Defender for the Besaid Aurochs",
    "uid": "OWWIypVjSEVEH4oYbm4lPSSvxXC3",
    "teamId": "team1"
  },
  "player6": {
    "imageUrl": "https://vignette.wikia.nocookie.net/finalfantasy/images/b/b9/Botta.jpg/revision/latest?cb=20111203055525",
    "title": "Botta",
    "description": "Right Defender for the Besaid Aurochs",
    "uid": "OWWIypVjSEVEH4oYbm4lPSSvxXC3",
    "teamId": "team1"
  },
  "player7": {
    "imageUrl": "https://vignette.wikia.nocookie.net/finalfantasy/images/b/b5/Keepa.jpg/revision/latest?cb=20111203055746",
    "title": "Keepa",
    "description": "Goal Keeper for the Besaid Aurochs",
    "uid": "OWWIypVjSEVEH4oYbm4lPSSvxXC3",
    "teamId": "team1"
  },
  "player8": {
    "imageUrl": "https://vignette.wikia.nocookie.net/finalfantasy/images/0/02/Chappu.png/revision/latest/scale-to-width-down/350?cb=20130115043845",
    "title": "Chappu",
    "description": "Late starting Left forward for the Besaid Aurochs. Chappu died tragically to Sin.",
    "uid": "OWWIypVjSEVEH4oYbm4lPSSvxXC3",
    "teamId": "team1"
  },
  "player9": {
    "imageUrl": "https://vignette.wikia.nocookie.net/finalfantasy/images/9/90/Bickson2.jpg/revision/latest?cb=20111203062954",
    "title": "Bickson",
    "description": "Team Captain and Left Forward for the Luca Goers",
    "uid": "OWWIypVjSEVEH4oYbm4lPSSvxXC3",
    "teamId": "team2"
  },
  "player10": {
    "imageUrl": "https://vignette.wikia.nocookie.net/finalfantasy/images/0/05/Abus.jpg/revision/latest?cb=20110519035059",
    "title": "Abus",
    "description": "Right Forward for the Luca Goers",
    "uid": "OWWIypVjSEVEH4oYbm4lPSSvxXC3",
    "teamId": "team2"
  },
  "player11": {
    "imageUrl": "https://vignette.wikia.nocookie.net/finalfantasy/images/1/11/Graav.jpg/revision/latest?cb=20111203062216",
    "title": "Graav",
    "description": "Midfielder for the Luca Goers",
    "uid": "OWWIypVjSEVEH4oYbm4lPSSvxXC3",
    "teamId": "team2"
  },
  "player12": {
    "imageUrl": "https://vignette.wikia.nocookie.net/finalfantasy/images/a/ad/Doram.jpg/revision/latest?cb=20111203062433",
    "title": "Doram",
    "description": "Left Defender for the Luca Goers",
    "uid": "OWWIypVjSEVEH4oYbm4lPSSvxXC3",
    "teamId": "team2"
  },
  "player13": {
    "imageUrl": "https://vignette.wikia.nocookie.net/finalfantasy/images/4/49/Balgerda.jpg/revision/latest?cb=20110519035818",
    "title": "Balgerda",
    "description": "Right Defender for the Luca Goers",
    "uid": "OWWIypVjSEVEH4oYbm4lPSSvxXC3",
    "teamId": "team2"
  },
  "player14": {
    "imageUrl": "https://vignette.wikia.nocookie.net/finalfantasy/images/8/84/Blitzballgame.jpeg/revision/latest?cb=20051128143525",
    "title": "Raudy",
    "description": "Goal Keeper for the Luca Goers",
    "uid": "OWWIypVjSEVEH4oYbm4lPSSvxXC3",
    "teamId": "team2"
  },
  "player15": {
    "imageUrl": "https://finalfantasy.fandom.com/wiki/Eigaar?file=Eigaar.jpg",
    "title": "Eigaar",
    "description": "Starting Left Forward for the Al Bhed Psyches",
    "uid": "12345",
    "teamId": "team3"
  },
  "player16": {
    "imageUrl": "https://finalfantasy.fandom.com/wiki/Blappa?file=Blappa2.jpg",
    "title": "Blappa",
    "description": "Right Forward for the Al Bhed Psyches",
    "uid": "12345",
    "teamId": "team3"
  },
  "player17": {
    "imageUrl": "https://finalfantasy.fandom.com/wiki/Berrik?file=Berrik.jpg",
    "title": "Berrik",
    "description": "Team Captain and Midfielder for the Al Bhed Psyches",
    "uid": "12345",
    "teamId": "team3"
  },
  "player18": {
    "imageUrl": "https://finalfantasy.fandom.com/wiki/Judda?file=Judda.jpg",
    "title": "Judda",
    "description": "Left Defender for the Al Bhed Psyches",
    "uid": "12345",
    "teamId": "team3"
  },
  "player19": {
    "imageUrl": "https://finalfantasy.fandom.com/wiki/Lakkam?file=Lakkam.jpg",
    "title": "Lakkam",
    "description": "Right Defender for the Al Bhed Psyches",
    "uid": "12345",
    "teamId": "team"
  },
  "player20": {
    "imageUrl": "https://finalfantasy.fandom.com/wiki/Nimrook?file=Nimrook.jpg",
    "title": "Nimrook",
    "description": "Goal Keeper for the Al Bhed Psyches",
    "uid": "12345",
    "teamId": "team3"
  }
}